[{"tid":"1","token":"ke371rgckorogochocdc","participant_info":{"firstname":"ke371rgckorogochocdc","lastname":"ke371rgckorogochocdc","email":"ke371rgckorogochocdc@gmail.com"}},{"tid":"3","token":"ke372rgchurumacdc","participant_info":{"firstname":"ke372rgchurumacdc","lastname":"ke372rgchurumacdc","email":"ke372rgchurumacdc@gmail.com"}},{"tid":"5","token":"ke373rgcmatharecdc","participant_info":{"firstname":"ke373rgcmatharecdc","lastname":"ke373rgcmatharecdc","email":"ke373rgcmatharecdc@gmail.com"}},{"tid":"7","token":"ke383umojakagcdc","participant_info":{"firstname":"ke383umojakagcdc","lastname":"ke383umojakagcdc","email":"ke383umojakagcdc@gmail.com"}},{"tid":"9","token":"ke439kalolenicogcdc","participant_info":{"firstname":"ke439kalolenicogcdc","lastname":"ke439kalolenicogcdc","email":"ke439kalolenicogcdc@gmail.com"}},{"tid":"11","token":"ke463cdckjfm","participant_info":{"firstname":"ke463cdckjfm","lastname":"ke463cdckjfm","email":"ke463cdckjfm@gmail.com"}},{"tid":"13","token":"ke528dandoracdc","participant_info":{"firstname":"ke528dandoracdc","lastname":"ke528dandoracdc","email":"ke528dandoracdc@gmail.com"}},{"tid":"15","token":"ke727jerichoaic","participant_info":{"firstname":"ke727jerichoaic","lastname":"ke727jerichoaic","email":"ke727jerichoaic@gmail.com"}},{"tid":"17","token":"lifespringke756","participant_info":{"firstname":"lifespringke756","lastname":"lifespringke756","email":"lifespringke756@gmail.com"}},{"tid":"19","token":"ke909pceakariobangincdc","participant_info":{"firstname":"ke909pceakariobangincdc","lastname":"ke909pceakariobangincdc","email":"ke909pceakariobangincdc@gmail.com"}},{"tid":"21","token":"ke910barakacdc","participant_info":{"firstname":"ke910barakacdc","lastname":"ke910barakacdc","email":"ke910barakacdc@gmail.com"}},{"tid":"23","token":"ke262cdcdeliverance","participant_info":{"firstname":"ke262cdcdeliverance","lastname":"ke262cdcdeliverance","email":"ke262cdcdeliverance@gmail.com"}},{"tid":"25","token":"ke301cdc","participant_info":{"firstname":"ke301cdc","lastname":"ke301cdc","email":"ke301cdc@gmail.com"}},{"tid":"27","token":"ke352dckiseriancdc","participant_info":{"firstname":"ke352dckiseriancdc","lastname":"ke352dckiseriancdc","email":"ke352dckiseriancdc@gmail.com"}},{"tid":"29","token":"ke354dcorongaicdc","participant_info":{"firstname":"ke354dcorongaicdc","lastname":"ke354dcorongaicdc","email":"ke354dcorongaicdc@gmail.com"}},{"tid":"31","token":"ke382cdc","participant_info":{"firstname":"ke382cdc","lastname":"ke382cdc","email":"ke382cdc@gmail.com"}},{"tid":"33","token":"ke407kangemicogcdc","participant_info":{"firstname":"ke407kangemicogcdc","lastname":"ke407kangemicogcdc","email":"ke407kangemicogcdc@gmail.com"}},{"tid":"35","token":"ke423kiberacdc","participant_info":{"firstname":"ke423kiberacdc","lastname":"ke423kiberacdc","email":"ke423kiberacdc@gmail.com"}},{"tid":"37","token":"ke715lavington","participant_info":{"firstname":"ke715lavington","lastname":"ke715lavington","email":"ke715lavington@gmail.com"}},{"tid":"39","token":"ke754pceaembulbul","participant_info":{"firstname":"ke754pceaembulbul","lastname":"ke754pceaembulbul","email":"ke754pceaembulbul@gmail.com"}},{"tid":"41","token":"ke755aiccdc","participant_info":{"firstname":"ke755aiccdc","lastname":"ke755aiccdc","email":"ke755aiccdc@gmail.com"}},{"tid":"43","token":"ke912cdc","participant_info":{"firstname":"ke912cdc","lastname":"ke912cdc","email":"ke912cdc@gmail.com"}},{"tid":"45","token":"ke916pceaemmanuelcdc","participant_info":{"firstname":"ke916pceaemmanuelcdc","lastname":"ke916pceaemmanuelcdc","email":"ke916pceaemmanuelcdc@gmail.com"}},{"tid":"47","token":"ke322kagfreeareacdsp","participant_info":{"firstname":"ke322kagfreeareacdsp","lastname":"ke322kagfreeareacdsp","email":"ke322kagfreeareacdsp@gmail.com"}},{"tid":"49","token":"ke348fpfksolaicdc","participant_info":{"firstname":"ke348fpfksolaicdc","lastname":"ke348fpfksolaicdc","email":"ke348fpfksolaicdc@gmail.com"}},{"tid":"51","token":"ke357childofdestinycdc","participant_info":{"firstname":"ke357childofdestinycdc","lastname":"ke357childofdestinycdc","email":"ke357childofdestinycdc@gmail.com"}},{"tid":"53","token":"ke386fpfkkabazicdc","participant_info":{"firstname":"ke386fpfkkabazicdc","lastname":"ke386fpfkkabazicdc","email":"ke386fpfkkabazicdc@gmail.com"}},{"tid":"55","token":"ke490agapesanctuaryminnkr","participant_info":{"firstname":"ke490agapesanctuaryminnkr","lastname":"ke490agapesanctuaryminnkr","email":"ke490agapesanctuaryminnkr@gmail.com"}},{"tid":"57","token":"ke507solaibaptist15","participant_info":{"firstname":"ke507solaibaptist15","lastname":"ke507solaibaptist15","email":"ke507solaibaptist15@gmail.com"}},{"tid":"59","token":"ke605fgckndungiricdc","participant_info":{"firstname":"ke605fgckndungiricdc","lastname":"ke605fgckndungiricdc","email":"ke605fgckndungiricdc@gmail.com"}},{"tid":"61","token":"ke610ackrongaicdc","participant_info":{"firstname":"ke610ackrongaicdc","lastname":"ke610ackrongaicdc","email":"ke610ackrongaicdc@gmail.com"}},{"tid":"63","token":"ke725aiclochoraicdc","participant_info":{"firstname":"ke725aiclochoraicdc","lastname":"ke725aiclochoraicdc","email":"ke725aiclochoraicdc@gmail.com"}},{"tid":"65","token":"ke726aicnjorotowncdc","participant_info":{"firstname":"ke726aicnjorotowncdc","lastname":"ke726aicnjorotowncdc","email":"ke726aicnjorotowncdc@googlemail.com"}},{"tid":"67","token":"ke906pceaelburgoncdp","participant_info":{"firstname":"ke906pceaelburgoncdp","lastname":"ke906pceaelburgoncdp","email":"ke906pceaelburgoncdp@gmail.com"}},{"tid":"69","token":"ke918pceakienicdc","participant_info":{"firstname":"ke918pceakienicdc","lastname":"ke918pceakienicdc","email":"ke918pceakienicdc@gmail.com"}},{"tid":"71","token":"ke922pceakagotocdc","participant_info":{"firstname":"ke922pceakagotocdc","lastname":"ke922pceakagotocdc","email":"ke922pceakagotocdc@gmail.com"}},{"tid":"73","token":"ke464aicnamuncha","participant_info":{"firstname":"ke464aicnamuncha","lastname":"ke464aicnamuncha","email":"ke464aicnamuncha@gmail.com"}},{"tid":"75","token":"ke465entashatabaptistcdc","participant_info":{"firstname":"ke465entashatabaptistcdc","lastname":"ke465entashatabaptistcdc","email":"ke465entashatabaptistcdc@gmail.com"}},{"tid":"77","token":"ke466aiceoremayian","participant_info":{"firstname":"ke466aiceoremayian","lastname":"ke466aiceoremayian","email":"ke466aiceoremayian@gmail.com"}},{"tid":"79","token":"ke589fgckcdc","participant_info":{"firstname":"ke589fgckcdc","lastname":"ke589fgckcdc","email":"ke589fgckcdc@gmail.com"}},{"tid":"81","token":"ke590cdc","participant_info":{"firstname":"ke590cdc","lastname":"ke590cdc","email":"ke590cdc@gmail.com"}},{"tid":"83","token":"ke0591","participant_info":{"firstname":"ke0591","lastname":"ke0591","email":"ke0591@gmail.com"}},{"tid":"85","token":"ke593cdc","participant_info":{"firstname":"ke593cdc","lastname":"ke593cdc","email":"ke593cdc@gmail.com"}},{"tid":"87","token":"ke599kagoloroito","participant_info":{"firstname":"ke599kagoloroito","lastname":"ke599kagoloroito","email":"ke599kagoloroito@gmail.com"}},{"tid":"89","token":"ke738aicempeut","participant_info":{"firstname":"ke738aicempeut","lastname":"ke738aicempeut","email":"ke738aicempeut@gmail.com"}},{"tid":"91","token":"ke822olesharoaic","participant_info":{"firstname":"ke822olesharoaic","lastname":"ke822olesharoaic","email":"ke822olesharoaic@gmail.com"}},{"tid":"93","token":"ke823baptistolorropil","participant_info":{"firstname":"ke823baptistolorropil","lastname":"ke823baptistolorropil","email":"ke823baptistolorropil@gmail.com"}},{"tid":"95","token":"ke824ewuasongirocdc","participant_info":{"firstname":"ke824ewuasongirocdc","lastname":"ke824ewuasongirocdc","email":"ke824ewuasongirocdc@gmail.com"}},{"tid":"97","token":"ke826aickarima","participant_info":{"firstname":"ke826aickarima","lastname":"ke826aickarima","email":"ke826aickarima@gmail.com"}},{"tid":"99","token":"ke900pomcoseronyokie","participant_info":{"firstname":"ke900pomcoseronyokie","lastname":"ke900pomcoseronyokie","email":"ke900pomcoseronyokie@gmail.com"}},{"tid":"101","token":"ke901pomcnajile","participant_info":{"firstname":"ke901pomcnajile","lastname":"ke901pomcnajile","email":"ke901pomcnajile@gmail.com"}},{"tid":"103","token":"ke324kaggithunguchu","participant_info":{"firstname":"ke324kaggithunguchu","lastname":"ke324kaggithunguchu","email":"ke324kaggithunguchu@gmail.com"}},{"tid":"105","token":"ke326kagrwamburichurchcdc","participant_info":{"firstname":"ke326kagrwamburichurchcdc","lastname":"ke326kagrwamburichurchcdc","email":"ke326kagrwamburichurchcdc@gmail.com"}},{"tid":"107","token":"ke620ackdagoretti","participant_info":{"firstname":"ke620ackdagoretti","lastname":"ke620ackdagoretti","email":"ke620ackdagoretti@gmail.com"}},{"tid":"109","token":"ke720nderu","participant_info":{"firstname":"ke720nderu","lastname":"ke720nderu","email":"ke720nderu@gmail.com"}},{"tid":"111","token":"ke722aicthigio","participant_info":{"firstname":"ke722aicthigio","lastname":"ke722aicthigio","email":"ke722aicthigio@gmail.com"}},{"tid":"113","token":"ke723aickamangu","participant_info":{"firstname":"ke723aickamangu","lastname":"ke723aickamangu","email":"ke723aickamangu@gmail.com"}},{"tid":"115","token":"ke733aicgitutha","participant_info":{"firstname":"ke733aicgitutha","lastname":"ke733aicgitutha","email":"ke733aicgitutha@gmail.com"}},{"tid":"117","token":"ke734aicndarakwa","participant_info":{"firstname":"ke734aicndarakwa","lastname":"ke734aicndarakwa","email":"ke734aicndarakwa@gmail.com"}},{"tid":"119","token":"ke736aicnachu","participant_info":{"firstname":"ke736aicnachu","lastname":"ke736aicnachu","email":"ke736aicnachu@gmail.com"}},{"tid":"121","token":"ke758aickanaan","participant_info":{"firstname":"ke758aickanaan","lastname":"ke758aickanaan","email":"ke758aickanaan@gmail.com"}},{"tid":"123","token":"ke903pceathogoto","participant_info":{"firstname":"ke903pceathogoto","lastname":"ke903pceathogoto","email":"ke903pceathogoto@gmail.com"}},{"tid":"125","token":"ke914pceatiekunu","participant_info":{"firstname":"ke914pceatiekunu","lastname":"ke914pceatiekunu","email":"ke914pceatiekunu@gmail.com"}},{"tid":"127","token":"ke230ackfaithchurchcdc","participant_info":{"firstname":"ke230ackfaithchurchcdc","lastname":"ke230ackfaithchurchcdc","email":"ke230ackfaithchurchcdc@gmail.com"}},{"tid":"129","token":"ke242oloikarra","participant_info":{"firstname":"ke242oloikarra","lastname":"ke242oloikarra","email":"ke242oloikarra@gmail.com"}},{"tid":"131","token":"ke368mashurupefacdc","participant_info":{"firstname":"ke368mashurupefacdc","lastname":"ke368mashurupefacdc","email":"ke368mashurupefacdc@gmail.com"}},{"tid":"133","token":"ke369pefaarroicdc","participant_info":{"firstname":"ke369pefaarroicdc","lastname":"ke369pefaarroicdc","email":"ke369pefaarroicdc@gmail.com"}},{"tid":"135","token":"ke374pefasultanhamudcdc","participant_info":{"firstname":"ke374pefasultanhamudcdc","lastname":"ke374pefasultanhamudcdc","email":"ke374pefasultanhamudcdc@gmail.com"}},{"tid":"137","token":"ke375pefakiimakiucdc","participant_info":{"firstname":"ke375pefakiimakiucdc","lastname":"ke375pefakiimakiucdc","email":"ke375pefakiimakiucdc@gmail.com"}},{"tid":"139","token":"ke550pefaimarorocdc","participant_info":{"firstname":"ke550pefaimarorocdc","lastname":"ke550pefaimarorocdc","email":"ke550pefaimarorocdc@gmail.com"}},{"tid":"141","token":"ke551kilobaptistcdc","participant_info":{"firstname":"ke551kilobaptistcdc","lastname":"ke551kilobaptistcdc","email":"ke551kilobaptistcdc@gmail.com"}},{"tid":"143","token":"ke633ackngatucdc","participant_info":{"firstname":"ke633ackngatucdc","lastname":"ke633ackngatucdc","email":"ke633ackngatucdc@gmail.com"}},{"tid":"145","token":"ke634ngaambacdc","participant_info":{"firstname":"ke634ngaambacdc","lastname":"ke634ngaambacdc","email":"ke634ngaambacdc@gmail.com"}},{"tid":"147","token":"ke729aickiucdcentre","participant_info":{"firstname":"ke729aickiucdcentre","lastname":"ke729aickiucdcentre","email":"ke729aickiucdcentre@gmail.com"}},{"tid":"149","token":"ke735cdcaickwale","participant_info":{"firstname":"ke735cdcaickwale","lastname":"ke735cdcaickwale","email":"ke735cdcaickwale@gmail.com"}},{"tid":"151","token":"ke920pceakibini","participant_info":{"firstname":"ke920pceakibini","lastname":"ke920pceakibini","email":"ke920pceakibini@gmail.com"}},{"tid":"153","token":"ke484ackstphilipsbungule","participant_info":{"firstname":"ke484ackstphilipsbungule","lastname":"ke484ackstphilipsbungule","email":"ke484ackstphilipsbungule@gmail.com"}},{"tid":"155","token":"ke485aicmahandakinicdc","participant_info":{"firstname":"ke485aicmahandakinicdc","lastname":"ke485aicmahandakinicdc","email":"ke485aicmahandakinicdc@gmail.com"}},{"tid":"157","token":"ke486aicmakutanocdc","participant_info":{"firstname":"ke486aicmakutanocdc","lastname":"ke486aicmakutanocdc","email":"ke486aicmakutanocdc@gmail.com"}},{"tid":"159","token":"ke487ackstmarymatacdc","participant_info":{"firstname":"ke487ackstmarymatacdc","lastname":"ke487ackstmarymatacdc","email":"ke487ackstmarymatacdc@gmail.com"}},{"tid":"161","token":"ke488aicvoicdc","participant_info":{"firstname":"ke488aicvoicdc","lastname":"ke488aicvoicdc","email":"ke488aicvoicdc@gmail.com"}},{"tid":"163","token":"ke489bugutaeternitycdc","participant_info":{"firstname":"ke489bugutaeternitycdc","lastname":"ke489bugutaeternitycdc","email":"ke489bugutaeternitycdc@gmail.com"}},{"tid":"165","token":"ke221olopicdc","participant_info":{"firstname":"ke221olopicdc","lastname":"ke221olopicdc","email":"ke221olopicdc@gmail.com"}},{"tid":"167","token":"ke253pefaikerege","participant_info":{"firstname":"ke253pefaikerege","lastname":"ke253pefaikerege","email":"ke253pefaikerege@gmail.com"}},{"tid":"169","token":"ke254pefamigoricdc","participant_info":{"firstname":"ke254pefamigoricdc","lastname":"ke254pefamigoricdc","email":"ke254pefamigoricdc@gmail.com"}},{"tid":"171","token":"ke316oldanyatimaranathacdc","participant_info":{"firstname":"ke316oldanyatimaranathacdc","lastname":"ke316oldanyatimaranathacdc","email":"ke316oldanyatimaranathacdc@gmail.com"}},{"tid":"173","token":"ke428mashangwacdc","participant_info":{"firstname":"ke428mashangwacdc","lastname":"ke428mashangwacdc","email":"ke428mashangwacdc@gmail.com"}},{"tid":"175","token":"ke429oldonyorokcdc","participant_info":{"firstname":"ke429oldonyorokcdc","lastname":"ke429oldonyorokcdc","email":"ke429oldonyorokcdc@gmail.com"}},{"tid":"177","token":"ke430maranathacdc","participant_info":{"firstname":"ke430maranathacdc","lastname":"ke430maranathacdc","email":"ke430maranathacdc@gmail.com"}},{"tid":"179","token":"ke431isokoncdc","participant_info":{"firstname":"ke431isokoncdc","lastname":"ke431isokoncdc","email":"ke431isokoncdc@gmail.com"}},{"tid":"181","token":"ke432lolgoriancdc","participant_info":{"firstname":"ke432lolgoriancdc","lastname":"ke432lolgoriancdc","email":"ke432lolgoriancdc@gmail.com"}},{"tid":"183","token":"ke467ackmasurura","participant_info":{"firstname":"ke467ackmasurura","lastname":"ke467ackmasurura","email":"ke467ackmasurura@gmail.com"}},{"tid":"185","token":"ke717methodistshankoecdc","participant_info":{"firstname":"ke717methodistshankoecdc","lastname":"ke717methodistshankoecdc","email":"ke717methodistshankoecdc@gmail.com"}},{"tid":"187","token":"ke731kilgorisscdcaic","participant_info":{"firstname":"ke731kilgorisscdcaic","lastname":"ke731kilgorisscdcaic","email":"ke731kilgorisscdcaic@gmail.com"}},{"tid":"189","token":"ke732enkopitcdc","participant_info":{"firstname":"ke732enkopitcdc","lastname":"ke732enkopitcdc","email":"ke732enkopitcdc@gmail.com"}},{"tid":"191","token":"ke401cogemmabwicdc","participant_info":{"firstname":"ke401cogemmabwicdc","lastname":"ke401cogemmabwicdc","email":"ke401cogemmabwicdc@gmail.com"}},{"tid":"193","token":"ke415cogekambulicdc","participant_info":{"firstname":"ke415cogekambulicdc","lastname":"ke415cogekambulicdc","email":"ke415cogekambulicdc@gmail.com"}},{"tid":"195","token":"ke801ackeluhobecdc","participant_info":{"firstname":"ke801ackeluhobecdc","lastname":"ke801ackeluhobecdc","email":"ke801ackeluhobecdc@gmail.com"}},{"tid":"197","token":"ke802ackmasenocdc","participant_info":{"firstname":"ke802ackmasenocdc","lastname":"ke802ackmasenocdc","email":"ke802ackmasenocdc@gmail.com"}},{"tid":"199","token":"ke810ackrawacdc1","participant_info":{"firstname":"ke810ackrawacdc1","lastname":"ke810ackrawacdc1","email":"ke810ackrawacdc1@gmail.com"}},{"tid":"201","token":"ke299kongoweamckcdc","participant_info":{"firstname":"ke299kongoweamckcdc","lastname":"ke299kongoweamckcdc","email":"ke299kongoweamckcdc@gmail.com"}},{"tid":"203","token":"ke330maambacdc","participant_info":{"firstname":"ke330maambacdc","lastname":"ke330maambacdc","email":"ke330maambacdc@gmail.com"}},{"tid":"205","token":"ke335mzambaraunicdc","participant_info":{"firstname":"ke335mzambaraunicdc","lastname":"ke335mzambaraunicdc","email":"ke335mzambaraunicdc@gmail.com"}},{"tid":"207","token":"ke336mwatundocdc1","participant_info":{"firstname":"ke336mwatundocdc1","lastname":"ke336mwatundocdc1","email":"ke336mwatundocdc1@gmail.com"}},{"tid":"209","token":"ke390mkwajunipefacdc","participant_info":{"firstname":"ke390mkwajunipefacdc","lastname":"ke390mkwajunipefacdc","email":"ke390mkwajunipefacdc@gmail.com"}},{"tid":"211","token":"ke391vumagrccdc","participant_info":{"firstname":"ke391vumagrccdc","lastname":"ke391vumagrccdc","email":"ke391vumagrccdc@gmail.com"}},{"tid":"213","token":"ke424kongoweacogcdc","participant_info":{"firstname":"ke424kongoweacogcdc","lastname":"ke424kongoweacogcdc","email":"ke424kongoweacogcdc@gmail.com"}},{"tid":"215","token":"ke504kiembenibaptistcdc","participant_info":{"firstname":"ke504kiembenibaptistcdc","lastname":"ke504kiembenibaptistcdc","email":"ke504kiembenibaptistcdc@gmail.com"}},{"tid":"217","token":"ke506victoriacdc","participant_info":{"firstname":"ke506victoriacdc","lastname":"ke506victoriacdc","email":"ke506victoriacdc@gmail.com"}},{"tid":"219","token":"ke508pceakisaunicdc","participant_info":{"firstname":"ke508pceakisaunicdc","lastname":"ke508pceakisaunicdc","email":"ke508pceakisaunicdc@gmail.com"}},{"tid":"221","token":"ke531shaurimoyolighthousecdc","participant_info":{"firstname":"ke531shaurimoyolighthousecdc","lastname":"ke531shaurimoyolighthousecdc","email":"ke531shaurimoyolighthousecdc@gmail.com"}},{"tid":"223","token":"ke640ackstmathewscdc","participant_info":{"firstname":"ke640ackstmathewscdc","lastname":"ke640ackstmathewscdc","email":"ke640ackstmathewscdc@gmail.com"}},{"tid":"225","token":"ke760aictudorcdc","participant_info":{"firstname":"ke760aictudorcdc","lastname":"ke760aictudorcdc","email":"ke760aictudorcdc@gmail.com"}},{"tid":"227","token":"ke761aicshanzucdc","participant_info":{"firstname":"ke761aicshanzucdc","lastname":"ke761aicshanzucdc","email":"ke761aicshanzucdc@gmail.com"}},{"tid":"229","token":"ke762eapckijipwacdc","participant_info":{"firstname":"ke762eapckijipwacdc","lastname":"ke762eapckijipwacdc","email":"ke762eapckijipwacdc@gmail.com"}},{"tid":"231","token":"ke475aicsandai","participant_info":{"firstname":"ke475aicsandai","lastname":"ke475aicsandai","email":"ke475aicsandai@gmail.com"}},{"tid":"233","token":"ke476aicchemolingot","participant_info":{"firstname":"ke476aicchemolingot","lastname":"ke476aicchemolingot","email":"ke476aicchemolingot@gmail.com"}},{"tid":"235","token":"ke477baptistloongeiwuan","participant_info":{"firstname":"ke477baptistloongeiwuan","lastname":"ke477baptistloongeiwuan","email":"ke477baptistloongeiwuan@gmail.com"}},{"tid":"237","token":"ke478fgckmarigat","participant_info":{"firstname":"ke478fgckmarigat","lastname":"ke478fgckmarigat","email":"ke478fgckmarigat@gmail.com"}},{"tid":"239","token":"ke479fgcksibilo","participant_info":{"firstname":"ke479fgcksibilo","lastname":"ke479fgcksibilo","email":"ke479fgcksibilo@gmail.com"}},{"tid":"241","token":"ke480fgckkibingor","participant_info":{"firstname":"ke480fgckkibingor","lastname":"ke480fgckkibingor","email":"ke480fgckkibingor@gmail.com"}},{"tid":"243","token":"ke216acknambalecdc","participant_info":{"firstname":"ke216acknambalecdc","lastname":"ke216acknambalecdc","email":"ke216acknambalecdc@gmail.com"}},{"tid":"245","token":"ke435ackmayenjecdc","participant_info":{"firstname":"ke435ackmayenjecdc","lastname":"ke435ackmayenjecdc","email":"ke435ackmayenjecdc@gmail.com"}},{"tid":"247","token":"ke437acknamaindicdc","participant_info":{"firstname":"ke437acknamaindicdc","lastname":"ke437acknamaindicdc","email":"ke437acknamaindicdc@gmail.com"}},{"tid":"249","token":"ke438ctmurumbacdc","participant_info":{"firstname":"ke438ctmurumbacdc","lastname":"ke438ctmurumbacdc","email":"ke438ctmurumbacdc@gmail.com"}},{"tid":"251","token":"ke440deliverancebusiacdc","participant_info":{"firstname":"ke440deliverancebusiacdc","lastname":"ke440deliverancebusiacdc","email":"ke440deliverancebusiacdc@gmail.com"}},{"tid":"253","token":"ke442ackbudokomicdc","participant_info":{"firstname":"ke442ackbudokomicdc","lastname":"ke442ackbudokomicdc","email":"ke442ackbudokomicdc@gmail.com"}},{"tid":"255","token":"ke443ackbuyofucdc","participant_info":{"firstname":"ke443ackbuyofucdc","lastname":"ke443ackbuyofucdc","email":"ke443ackbuyofucdc@gmail.com"}},{"tid":"257","token":"ke452joeadungosicdc","participant_info":{"firstname":"ke452joeadungosicdc","lastname":"ke452joeadungosicdc","email":"ke452joeadungosicdc@gmail.com"}},{"tid":"259","token":"ke453fpfkcdc","participant_info":{"firstname":"ke453fpfkcdc","lastname":"ke453fpfkcdc","email":"ke453fpfkcdc@gmail.com"}},{"tid":"261","token":"ke454crcamukuracdc","participant_info":{"firstname":"ke454crcamukuracdc","lastname":"ke454crcamukuracdc","email":"ke454crcamukuracdc@gmail.com"}},{"tid":"263","token":"ke455fpfkaturetcdc","participant_info":{"firstname":"ke455fpfkaturetcdc","lastname":"ke455fpfkaturetcdc","email":"ke455fpfkaturetcdc@gmail.com"}},{"tid":"265","token":"ke456mrccsimbachai","participant_info":{"firstname":"ke456mrccsimbachai","lastname":"ke456mrccsimbachai","email":"ke456mrccsimbachai@gmail.com"}},{"tid":"267","token":"ke457mrcckoturcdc","participant_info":{"firstname":"ke457mrcckoturcdc","lastname":"ke457mrcckoturcdc","email":"ke457mrcckoturcdc@gmail.com"}},{"tid":"269","token":"ke458ackmalabacdc","participant_info":{"firstname":"ke458ackmalabacdc","lastname":"ke458ackmalabacdc","email":"ke458ackmalabacdc@gmail.com"}},{"tid":"271","token":"ke459ackstpaulsbudumacdc","participant_info":{"firstname":"ke459ackstpaulsbudumacdc","lastname":"ke459ackstpaulsbudumacdc","email":"ke459ackstpaulsbudumacdc@gmail.com"}},{"tid":"273","token":"ke255deliverancekendubay","participant_info":{"firstname":"ke255deliverancekendubay","lastname":"ke255deliverancekendubay","email":"ke255deliverancekendubay@gmail.com"}},{"tid":"275","token":"ke256fgckmasogocdc","participant_info":{"firstname":"ke256fgckmasogocdc","lastname":"ke256fgckmasogocdc","email":"ke256fgckmasogocdc@gmail.com"}},{"tid":"277","token":"ke257fgckoriang","participant_info":{"firstname":"ke257fgckoriang","lastname":"ke257fgckoriang","email":"ke257fgckoriang@gmail.com"}},{"tid":"279","token":"ke258fgcklwandacdc","participant_info":{"firstname":"ke258fgcklwandacdc","lastname":"ke258fgcklwandacdc","email":"ke258fgcklwandacdc@gmail.com"}},{"tid":"281","token":"ke259fgckrangombe","participant_info":{"firstname":"ke259fgckrangombe","lastname":"ke259fgckrangombe","email":"ke259fgckrangombe@gmail.com"}},{"tid":"283","token":"ke260pefahomabay","participant_info":{"firstname":"ke260pefahomabay","lastname":"ke260pefahomabay","email":"ke260pefahomabay@gmail.com"}},{"tid":"285","token":"ke261pefanyagorocdc","participant_info":{"firstname":"ke261pefanyagorocdc","lastname":"ke261pefanyagorocdc","email":"ke261pefanyagorocdc@gmail.com"}},{"tid":"287","token":"ke0270redeemedgospelchurch","participant_info":{"firstname":"ke0270redeemedgospelchurch","lastname":"ke0270redeemedgospelchurch","email":"ke0270redeemedgospelchurch@gmail.com"}},{"tid":"289","token":"ke0271aicrangwe","participant_info":{"firstname":"ke0271aicrangwe","lastname":"ke0271aicrangwe","email":"ke0271aicrangwe@gmail.com"}},{"tid":"291","token":"ke0272flwcriat","participant_info":{"firstname":"ke0272flwcriat","lastname":"ke0272flwcriat","email":"ke0272flwcriat@gmail.com"}},{"tid":"293","token":"ke0273baptistrusinga","participant_info":{"firstname":"ke0273baptistrusinga","lastname":"ke0273baptistrusinga","email":"ke0273baptistrusinga@gmail.com"}},{"tid":"295","token":"ke0274pefamfangano","participant_info":{"firstname":"ke0274pefamfangano","lastname":"ke0274pefamfangano","email":"ke0274pefamfangano@gmail.com"}},{"tid":"297","token":"ke200cdc","participant_info":{"firstname":"ke200cdc","lastname":"ke200cdc","email":"ke200cdc@gmail.com"}},{"tid":"299","token":"ke202cdc","participant_info":{"firstname":"ke202cdc","lastname":"ke202cdc","email":"ke202cdc@gmail.com"}},{"tid":"301","token":"ke204cdc","participant_info":{"firstname":"ke204cdc","lastname":"ke204cdc","email":"ke204cdc@gmail.com"}},{"tid":"303","token":"ke206cdc","participant_info":{"firstname":"ke206cdc","lastname":"ke206cdc","email":"ke206cdc@gmail.com"}},{"tid":"305","token":"ke207kamutucdc","participant_info":{"firstname":"ke207kamutucdc","lastname":"ke207kamutucdc","email":"ke207kamutucdc@gmail.com"}},{"tid":"307","token":"ke209ackkogaricdc","participant_info":{"firstname":"ke209ackkogaricdc","lastname":"ke209ackkogaricdc","email":"ke209ackkogaricdc@gmail.com"}},{"tid":"309","token":"ke211cdc","participant_info":{"firstname":"ke211cdc","lastname":"ke211cdc","email":"ke211cdc@gmail.com"}},{"tid":"311","token":"ke214cdc","participant_info":{"firstname":"ke214cdc","lastname":"ke214cdc","email":"ke214cdc@gmail.com"}},{"tid":"313","token":"ke217acksinaicdc","participant_info":{"firstname":"ke217acksinaicdc","lastname":"ke217acksinaicdc","email":"ke217acksinaicdc@gmail.com"}},{"tid":"315","token":"ke444pefamurigiishiara","participant_info":{"firstname":"ke444pefamurigiishiara","lastname":"ke444pefamurigiishiara","email":"ke444pefamurigiishiara@gmail.com"}},{"tid":"317","token":"ke445eapcmuthantharacdc","participant_info":{"firstname":"ke445eapcmuthantharacdc","lastname":"ke445eapcmuthantharacdc","email":"ke445eapcmuthantharacdc@gmail.com"}},{"tid":"319","token":"ke446eapcnthigiranicdc","participant_info":{"firstname":"ke446eapcnthigiranicdc","lastname":"ke446eapcnthigiranicdc","email":"ke446eapcnthigiranicdc@gmail.com"}},{"tid":"321","token":"ke447eapckiugucdc","participant_info":{"firstname":"ke447eapckiugucdc","lastname":"ke447eapckiugucdc","email":"ke447eapckiugucdc@gmail.com"}},{"tid":"323","token":"ke325aickatumanicdc","participant_info":{"firstname":"ke325aickatumanicdc","lastname":"ke325aickatumanicdc","email":"ke325aickatumanicdc@gmail.com"}},{"tid":"325","token":"ke552ilmamen","participant_info":{"firstname":"ke552ilmamen","lastname":"ke552ilmamen","email":"ke552ilmamen@gmail.com"}},{"tid":"327","token":"ke553lenchanibaptistcdc","participant_info":{"firstname":"ke553lenchanibaptistcdc","lastname":"ke553lenchanibaptistcdc","email":"ke553lenchanibaptistcdc@gmail.com"}},{"tid":"329","token":"ke554pefaoloontotocdc","participant_info":{"firstname":"ke554pefaoloontotocdc","lastname":"ke554pefaoloontotocdc","email":"ke554pefaoloontotocdc@gmail.com"}},{"tid":"331","token":"ke555pefaolturotocdc","participant_info":{"firstname":"ke555pefaolturotocdc","lastname":"ke555pefaolturotocdc","email":"ke555pefaolturotocdc@gmail.com"}},{"tid":"333","token":"ke588mckoloshaiki","participant_info":{"firstname":"ke588mckoloshaiki","lastname":"ke588mckoloshaiki","email":"ke588mckoloshaiki@gmail.com"}},{"tid":"335","token":"ke630icdsp","participant_info":{"firstname":"ke630icdsp","lastname":"ke630icdsp","email":"ke630icdsp@gmail.com"}},{"tid":"337","token":"ke631ackoloiriencdc","participant_info":{"firstname":"ke631ackoloiriencdc","lastname":"ke631ackoloiriencdc","email":"ke631ackoloiriencdc@gmail.com"}},{"tid":"339","token":"ke724manzacdsp","participant_info":{"firstname":"ke724manzacdsp","lastname":"ke724manzacdsp","email":"ke724manzacdsp@gmail.com"}},{"tid":"341","token":"ke742aickyenzenzeni","participant_info":{"firstname":"ke742aickyenzenzeni","lastname":"ke742aickyenzenzeni","email":"ke742aickyenzenzeni@gmail.com"}},{"tid":"343","token":"ke744aicmungalacdc","participant_info":{"firstname":"ke744aicmungalacdc","lastname":"ke744aicmungalacdc","email":"ke744aicmungalacdc@gmail.com"}},{"tid":"345","token":"ke753aickatoloni","participant_info":{"firstname":"ke753aickatoloni","lastname":"ke753aickatoloni","email":"ke753aickatoloni@gmail.com"}},{"tid":"347","token":"ke904pomcinkitocdc","participant_info":{"firstname":"ke904pomcinkitocdc","lastname":"ke904pomcinkitocdc","email":"ke904pomcinkitocdc@gmail.com"}},{"tid":"349","token":"ke905pceacdsp","participant_info":{"firstname":"ke905pceacdsp","lastname":"ke905pceacdsp","email":"ke905pceacdsp@gmail.com"}},{"tid":"351","token":"ke314eapcarcherscdc","participant_info":{"firstname":"ke314eapcarcherscdc","lastname":"ke314eapcarcherscdc","email":"ke314eapcarcherscdc@gmail.com"}},{"tid":"353","token":"ke614ackmugumocdc","participant_info":{"firstname":"ke614ackmugumocdc","lastname":"ke614ackmugumocdc","email":"ke614ackmugumocdc@gmail.com"}},{"tid":"355","token":"ke702isiolocdc","participant_info":{"firstname":"ke702isiolocdc","lastname":"ke702isiolocdc","email":"ke702isiolocdc@gmail.com"}},{"tid":"357","token":"ke703mwanamutethuacdc","participant_info":{"firstname":"ke703mwanamutethuacdc","lastname":"ke703mwanamutethuacdc","email":"ke703mwanamutethuacdc@gmail.com"}},{"tid":"359","token":"ke704murerwachild","participant_info":{"firstname":"ke704murerwachild","lastname":"ke704murerwachild","email":"ke704murerwachild@gmail.com"}},{"tid":"361","token":"ke705mckstmaryscd","participant_info":{"firstname":"ke705mckstmaryscd","lastname":"ke705mckstmaryscd","email":"ke705mckstmaryscd@gmail.com"}},{"tid":"363","token":"ke708muguna","participant_info":{"firstname":"ke708muguna","lastname":"ke708muguna","email":"ke708muguna@gmail.com"}},{"tid":"365","token":"ke713kisimacdc","participant_info":{"firstname":"ke713kisimacdc","lastname":"ke713kisimacdc","email":"ke713kisimacdc@gmail.com"}},{"tid":"367","token":"ke714mcklubunu","participant_info":{"firstname":"ke714mcklubunu","lastname":"ke714mcklubunu","email":"ke714mcklubunu@gmail.com"}},{"tid":"369","token":"ke785mckntumburicdc","participant_info":{"firstname":"ke785mckntumburicdc","lastname":"ke785mckntumburicdc","email":"ke785mckntumburicdc@gmail.com"}},{"tid":"371","token":"ke786stmathewscdc","participant_info":{"firstname":"ke786stmathewscdc","lastname":"ke786stmathewscdc","email":"ke786stmathewscdc@gmail.com"}},{"tid":"373","token":"ke792mckngusishicdc","participant_info":{"firstname":"ke792mckngusishicdc","lastname":"ke792mckngusishicdc","email":"ke792mckngusishicdc@gmail.com"}},{"tid":"375","token":"ke830mckngarendarecdc","participant_info":{"firstname":"ke830mckngarendarecdc","lastname":"ke830mckngarendarecdc","email":"ke830mckngarendarecdc@gmail.com"}},{"tid":"377","token":"ke915pceangeniacdc","participant_info":{"firstname":"ke915pceangeniacdc","lastname":"ke915pceangeniacdc","email":"ke915pceangeniacdc@gmail.com"}},{"tid":"379","token":"ke228ackmushililiecdc","participant_info":{"firstname":"ke228ackmushililiecdc","lastname":"ke228ackmushililiecdc","email":"ke228ackmushililiecdc@gmail.com"}},{"tid":"381","token":"ke360ivolapagcdc2009","participant_info":{"firstname":"ke360ivolapagcdc2009","lastname":"ke360ivolapagcdc2009","email":"ke360ivolapagcdc2009@gmail.com"}},{"tid":"383","token":"ke362pagamalembacdc","participant_info":{"firstname":"ke362pagamalembacdc","lastname":"ke362pagamalembacdc","email":"ke362pagamalembacdc@gmail.com"}},{"tid":"385","token":"ke366museywapagcdc","participant_info":{"firstname":"ke366museywapagcdc","lastname":"ke366museywapagcdc","email":"ke366museywapagcdc@gmail.com"}},{"tid":"387","token":"ke367musembecdc","participant_info":{"firstname":"ke367musembecdc","lastname":"ke367musembecdc","email":"ke367musembecdc@gmail.com"}},{"tid":"389","token":"ke380kipchekwencdc","participant_info":{"firstname":"ke380kipchekwencdc","lastname":"ke380kipchekwencdc","email":"ke380kipchekwencdc@gmail.com"}},{"tid":"391","token":"ke385afcealubao","participant_info":{"firstname":"ke385afcealubao","lastname":"ke385afcealubao","email":"ke385afcealubao@gmail.com"}},{"tid":"393","token":"ke416mahiakalocdc","participant_info":{"firstname":"ke416mahiakalocdc","lastname":"ke416mahiakalocdc","email":"ke416mahiakalocdc@gmail.com"}},{"tid":"395","token":"ke820ackagulucdc","participant_info":{"firstname":"ke820ackagulucdc","lastname":"ke820ackagulucdc","email":"ke820ackagulucdc@gmail.com"}},{"tid":"397","token":"ke821ambiracdc","participant_info":{"firstname":"ke821ambiracdc","lastname":"ke821ambiracdc","email":"ke821ambiracdc@gmail.com"}},{"tid":"399","token":"ke0510pefanyangerecydc","participant_info":{"firstname":"ke0510pefanyangerecydc","lastname":"ke0510pefanyangerecydc","email":"ke0510pefanyangerecydc@gmail.com"}},{"tid":"401","token":"ke0511pefakegongacydc","participant_info":{"firstname":"ke0511pefakegongacydc","lastname":"ke0511pefakegongacydc","email":"ke0511pefakegongacydc@gmail.com"}},{"tid":"403","token":"ke811ackyalacdc2","participant_info":{"firstname":"ke811ackyalacdc2","lastname":"ke811ackyalacdc2","email":"ke811ackyalacdc2@gmail.com"}},{"tid":"405","token":"ke0515ackbandecydc","participant_info":{"firstname":"ke0515ackbandecydc","lastname":"ke0515ackbandecydc","email":"ke0515ackbandecydc@gmail.com"}},{"tid":"407","token":"ke532casuarinacdc","participant_info":{"firstname":"ke532casuarinacdc","lastname":"ke532casuarinacdc","email":"ke532casuarinacdc@gmail.com"}},{"tid":"409","token":"ke534ushindibaptistcdc","participant_info":{"firstname":"ke534ushindibaptistcdc","lastname":"ke534ushindibaptistcdc","email":"ke534ushindibaptistcdc@gmail.com"}},{"tid":"411","token":"ke623standrewscdc","participant_info":{"firstname":"ke623standrewscdc","lastname":"ke623standrewscdc","email":"ke623standrewscdc@gmail.com"}},{"tid":"413","token":"ke624gedecdc","participant_info":{"firstname":"ke624gedecdc","lastname":"ke624gedecdc","email":"ke624gedecdc@gmail.com"}},{"tid":"415","token":"ke788rgcgongonicdc","participant_info":{"firstname":"ke788rgcgongonicdc","lastname":"ke788rgcgongonicdc","email":"ke788rgcgongonicdc@gmail.com"}},{"tid":"417","token":"ke793ackstclement","participant_info":{"firstname":"ke793ackstclement","lastname":"ke793ackstclement","email":"ke793ackstclement@gmail.com"}},{"tid":"419","token":"ke396kagmaralalcdc","participant_info":{"firstname":"ke396kagmaralalcdc","lastname":"ke396kagmaralalcdc","email":"ke396kagmaralalcdc@gmail.com"}},{"tid":"421","token":"ke397kagwambacdc","participant_info":{"firstname":"ke397kagwambacdc","lastname":"ke397kagwambacdc","email":"ke397kagwambacdc@gmail.com"}},{"tid":"423","token":"ke398kerithwambacdc","participant_info":{"firstname":"ke398kerithwambacdc","lastname":"ke398kerithwambacdc","email":"ke398kerithwambacdc@gmail.com"}},{"tid":"425","token":"ke399kisimacdc","participant_info":{"firstname":"ke399kisimacdc","lastname":"ke399kisimacdc","email":"ke399kisimacdc@gmail.com"}},{"tid":"427","token":"ke448eapcporocdc","participant_info":{"firstname":"ke448eapcporocdc","lastname":"ke448eapcporocdc","email":"ke448eapcporocdc@gmail.com"}},{"tid":"429","token":"ke612kirimoncdc","participant_info":{"firstname":"ke612kirimoncdc","lastname":"ke612kirimoncdc","email":"ke612kirimoncdc@gmail.com"}},{"tid":"431","token":"ke613ackloosukcdc","participant_info":{"firstname":"ke613ackloosukcdc","lastname":"ke613ackloosukcdc","email":"ke613ackloosukcdc@gmail.com"}},{"tid":"433","token":"ke667acksirata","participant_info":{"firstname":"ke667acksirata","lastname":"ke667acksirata","email":"ke667acksirata@gmail.com"}},{"tid":"435","token":"ke773aiclareoiborcdc","participant_info":{"firstname":"ke773aiclareoiborcdc","lastname":"ke773aiclareoiborcdc","email":"ke773aiclareoiborcdc@gmail.com"}},{"tid":"437","token":"ke799fgckmaralal","participant_info":{"firstname":"ke799fgckmaralal","lastname":"ke799fgckmaralal","email":"ke799fgckmaralal@gmail.com"}},{"tid":"439","token":"ke247aickorrcdc","participant_info":{"firstname":"ke247aickorrcdc","lastname":"ke247aickorrcdc","email":"ke247aickorrcdc@gmail.com"}},{"tid":"441","token":"ke248pceaboruharocdc","participant_info":{"firstname":"ke248pceaboruharocdc","lastname":"ke248pceaboruharocdc","email":"ke248pceaboruharocdc@gmail.com"}},{"tid":"443","token":"ke249acklaisamiscdc","participant_info":{"firstname":"ke249acklaisamiscdc","lastname":"ke249acklaisamiscdc","email":"ke249acklaisamiscdc@gmail.com"}},{"tid":"445","token":"ke250aickararecdc","participant_info":{"firstname":"ke250aickararecdc","lastname":"ke250aickararecdc","email":"ke250aickararecdc@gmail.com"}},{"tid":"447","token":"ke251fgcksereolipi","participant_info":{"firstname":"ke251fgcksereolipi","lastname":"ke251fgcksereolipi","email":"ke251fgcksereolipi@gmail.com"}},{"tid":"449","token":"ke252eapcmarsabitcdc","participant_info":{"firstname":"ke252eapcmarsabitcdc","lastname":"ke252eapcmarsabitcdc","email":"ke252eapcmarsabitcdc@gmail.com"}},{"tid":"451","token":"ke269aicmerillecdc","participant_info":{"firstname":"ke269aicmerillecdc","lastname":"ke269aicmerillecdc","email":"ke269aicmerillecdc@gmail.com"}},{"tid":"453","token":"ke0275fgckloglogocdc","participant_info":{"firstname":"ke0275fgckloglogocdc","lastname":"ke0275fgckloglogocdc","email":"ke0275fgckloglogocdc@gmail.com"}},{"tid":"455","token":"ke0276eccamoyalecdc","participant_info":{"firstname":"ke0276eccamoyalecdc","lastname":"ke0276eccamoyalecdc","email":"ke0276eccamoyalecdc@gmail.com"}},{"tid":"457","token":"ke0277ackmaikonacdc","participant_info":{"firstname":"ke0277ackmaikonacdc","lastname":"ke0277ackmaikonacdc","email":"ke0277ackmaikonacdc@gmail.com"}},{"tid":"459","token":"ke0278citamgororukesacdc","participant_info":{"firstname":"ke0278citamgororukesacdc","lastname":"ke0278citamgororukesacdc","email":"ke0278citamgororukesacdc@gmail.com"}},{"tid":"461","token":"ke0279aicdiripgombocdc","participant_info":{"firstname":"ke0279aicdiripgombocdc","lastname":"ke0279aicdiripgombocdc","email":"ke0279aicdiripgombocdc@gmail.com"}},{"tid":"463","token":"ke304fpfkkiriene","participant_info":{"firstname":"ke304fpfkkiriene","lastname":"ke304fpfkkiriene","email":"ke304fpfkkiriene@gmail.com"}},{"tid":"465","token":"ke323kagmerucdc","participant_info":{"firstname":"ke323kagmerucdc","lastname":"ke323kagmerucdc","email":"ke323kagmerucdc@gmail.com"}},{"tid":"467","token":"ke338mukothimacdc","participant_info":{"firstname":"ke338mukothimacdc","lastname":"ke338mukothimacdc","email":"ke338mukothimacdc@gmail.com"}},{"tid":"469","token":"ke339gatukucdc","participant_info":{"firstname":"ke339gatukucdc","lastname":"ke339gatukucdc","email":"ke339gatukucdc@gmail.com"}},{"tid":"471","token":"ke340kiamauticdc","participant_info":{"firstname":"ke340kiamauticdc","lastname":"ke340kiamauticdc","email":"ke340kiamauticdc@gmail.com"}},{"tid":"473","token":"ke425gatithinicdc","participant_info":{"firstname":"ke425gatithinicdc","lastname":"ke425gatithinicdc","email":"ke425gatithinicdc@gmail.com"}},{"tid":"475","token":"ke700mckkaagacdc","participant_info":{"firstname":"ke700mckkaagacdc","lastname":"ke700mckkaagacdc","email":"ke700mckkaagacdc@gmail.com"}},{"tid":"477","token":"ke701mckrunogonecdc1","participant_info":{"firstname":"ke701mckrunogonecdc1","lastname":"ke701mckrunogonecdc1","email":"ke701mckrunogonecdc1@gmail.com"}},{"tid":"479","token":"ke706kambereucdc","participant_info":{"firstname":"ke706kambereucdc","lastname":"ke706kambereucdc","email":"ke706kambereucdc@gmail.com"}},{"tid":"481","token":"ke707kiburinecdc","participant_info":{"firstname":"ke707kiburinecdc","lastname":"ke707kiburinecdc","email":"ke707kiburinecdc@gmail.com"}},{"tid":"483","token":"ke709mckikanacdc","participant_info":{"firstname":"ke709mckikanacdc","lastname":"ke709mckikanacdc","email":"ke709mckikanacdc@gmail.com"}},{"tid":"485","token":"ke718miomponicdc","participant_info":{"firstname":"ke718miomponicdc","lastname":"ke718miomponicdc","email":"ke718miomponicdc@gmail.com"}},{"tid":"487","token":"ke719mckthiiticdc","participant_info":{"firstname":"ke719mckthiiticdc","lastname":"ke719mckthiiticdc","email":"ke719mckthiiticdc@gmail.com"}},{"tid":"489","token":"ke739karoucdc","participant_info":{"firstname":"ke739karoucdc","lastname":"ke739karoucdc","email":"ke739karoucdc@gmail.com"}},{"tid":"491","token":"ke743nkondigfbccdc","participant_info":{"firstname":"ke743nkondigfbccdc","lastname":"ke743nkondigfbccdc","email":"ke743nkondigfbccdc@gmail.com"}},{"tid":"493","token":"ke333eapcnyalanikalolenicdc","participant_info":{"firstname":"ke333eapcnyalanikalolenicdc","lastname":"ke333eapcnyalanikalolenicdc","email":"ke333eapcnyalanikalolenicdc@gmail.com"}},{"tid":"495","token":"ke334mwelekaloleni","participant_info":{"firstname":"ke334mwelekaloleni","lastname":"ke334mwelekaloleni","email":"ke334mwelekaloleni@gmail.com"}},{"tid":"497","token":"ke358deliverancelikonicdc","participant_info":{"firstname":"ke358deliverancelikonicdc","lastname":"ke358deliverancelikonicdc","email":"ke358deliverancelikonicdc@gmail.com"}},{"tid":"499","token":"ke359deliverancekalolenicdc","participant_info":{"firstname":"ke359deliverancekalolenicdc","lastname":"ke359deliverancekalolenicdc","email":"ke359deliverancekalolenicdc@gmail.com"}},{"tid":"501","token":"ke427newtestamentcdc","participant_info":{"firstname":"ke427newtestamentcdc","lastname":"ke427newtestamentcdc","email":"ke427newtestamentcdc@gmail.com"}},{"tid":"503","token":"ke461ackstmarkscdc","participant_info":{"firstname":"ke461ackstmarkscdc","lastname":"ke461ackstmarkscdc","email":"ke461ackstmarkscdc@gmail.com"}},{"tid":"505","token":"ke468mariakanicdc","participant_info":{"firstname":"ke468mariakanicdc","lastname":"ke468mariakanicdc","email":"ke468mariakanicdc@gmail.com"}},{"tid":"507","token":"ke500changamwecdc","participant_info":{"firstname":"ke500changamwecdc","lastname":"ke500changamwecdc","email":"ke500changamwecdc@gmail.com"}},{"tid":"509","token":"ke505ushindicdc","participant_info":{"firstname":"ke505ushindicdc","lastname":"ke505ushindicdc","email":"ke505ushindicdc@gmail.com"}},{"tid":"511","token":"ke592madzimbanicdc","participant_info":{"firstname":"ke592madzimbanicdc","lastname":"ke592madzimbanicdc","email":"ke592madzimbanicdc@gmail.com"}},{"tid":"513","token":"ke642acksowetocdc","participant_info":{"firstname":"ke642acksowetocdc","lastname":"ke642acksowetocdc","email":"ke642acksowetocdc@gmail.com"}},{"tid":"515","token":"ke712mckmbungonicdc","participant_info":{"firstname":"ke712mckmbungonicdc","lastname":"ke712mckmbungonicdc","email":"ke712mckmbungonicdc@gmail.com"}},{"tid":"517","token":"ke740gncamtongwecdc","participant_info":{"firstname":"ke740gncamtongwecdc","lastname":"ke740gncamtongwecdc","email":"ke740gncamtongwecdc@gmail.com"}},{"tid":"519","token":"ke763chanagandeaic","participant_info":{"firstname":"ke763chanagandeaic","lastname":"ke763chanagandeaic","email":"ke763chanagandeaic@gmail.com"}},{"tid":"521","token":"ke227ackkamwerinecdc","participant_info":{"firstname":"ke227ackkamwerinecdc","lastname":"ke227ackkamwerinecdc","email":"ke227ackkamwerinecdc@gmail.com"}},{"tid":"523","token":"ke315eapckanthorokocdc","participant_info":{"firstname":"ke315eapckanthorokocdc","lastname":"ke315eapckanthorokocdc","email":"ke315eapckanthorokocdc@gmail.com"}},{"tid":"525","token":"ke349grckimangaocdc","participant_info":{"firstname":"ke349grckimangaocdc","lastname":"ke349grckimangaocdc","email":"ke349grckimangaocdc@gmail.com"}},{"tid":"527","token":"ke433kamayagichurchofgodcdc","participant_info":{"firstname":"ke433kamayagichurchofgodcdc","lastname":"ke433kamayagichurchofgodcdc","email":"ke433kamayagichurchofgodcdc@gmail.com"}},{"tid":"529","token":"ke469aicmwarangenicdc","participant_info":{"firstname":"ke469aicmwarangenicdc","lastname":"ke469aicmwarangenicdc","email":"ke469aicmwarangenicdc@gmail.com"}},{"tid":"531","token":"ke759aickanzinwacdc","participant_info":{"firstname":"ke759aickanzinwacdc","lastname":"ke759aickanzinwacdc","email":"ke759aickanzinwacdc@gmail.com"}},{"tid":"533","token":"ke767fgckkamuwongocdc","participant_info":{"firstname":"ke767fgckkamuwongocdc","lastname":"ke767fgckkamuwongocdc","email":"ke767fgckkamuwongocdc@gmail.com"}},{"tid":"535","token":"ke768fgckkasyalanicdc","participant_info":{"firstname":"ke768fgckkasyalanicdc","lastname":"ke768fgckkasyalanicdc","email":"ke768fgckkasyalanicdc@gmail.com"}},{"tid":"537","token":"ke770aicnzewanicdc","participant_info":{"firstname":"ke770aicnzewanicdc","lastname":"ke770aicnzewanicdc","email":"ke770aicnzewanicdc@gmail.com"}},{"tid":"539","token":"kyusoke771goccdc","participant_info":{"firstname":"kyusoke771goccdc","lastname":"kyusoke771goccdc","email":"kyusoke771goccdc@gmail.com"}},{"tid":"541","token":"ke772aicmbangwanicdc","participant_info":{"firstname":"ke772aicmbangwanicdc","lastname":"ke772aicmbangwanicdc","email":"ke772aicmbangwanicdc@gmail.com"}},{"tid":"543","token":"ke790aicnguukucdc","participant_info":{"firstname":"ke790aicnguukucdc","lastname":"ke790aicnguukucdc","email":"ke790aicnguukucdc@gmail.com"}},{"tid":"545","token":"ke212cdc","participant_info":{"firstname":"ke212cdc","lastname":"ke212cdc","email":"ke212cdc@gmail.com"}},{"tid":"547","token":"ke215cdc","participant_info":{"firstname":"ke215cdc","lastname":"ke215cdc","email":"ke215cdc@gmail.com"}},{"tid":"549","token":"ke224cdc","participant_info":{"firstname":"ke224cdc","lastname":"ke224cdc","email":"ke224cdc@gmail.com"}},{"tid":"551","token":"ke225cdc","participant_info":{"firstname":"ke225cdc","lastname":"ke225cdc","email":"ke225cdc@gmail.com"}},{"tid":"553","token":"ke226cdc","participant_info":{"firstname":"ke226cdc","lastname":"ke226cdc","email":"ke226cdc@gmail.com"}},{"tid":"555","token":"ke229ackngomolacdc","participant_info":{"firstname":"ke229ackngomolacdc","lastname":"ke229ackngomolacdc","email":"ke229ackngomolacdc@gmail.com"}},{"tid":"557","token":"ke231enacdc","participant_info":{"firstname":"ke231enacdc","lastname":"ke231enacdc","email":"ke231enacdc@gmail.com"}},{"tid":"559","token":"ke232ngurukacdc","participant_info":{"firstname":"ke232ngurukacdc","lastname":"ke232ngurukacdc","email":"ke232ngurukacdc@gmail.com"}},{"tid":"561","token":"ke378nthinginicdc","participant_info":{"firstname":"ke378nthinginicdc","lastname":"ke378nthinginicdc","email":"ke378nthinginicdc@gmail.com"}},{"tid":"563","token":"ke379ccigitaraka","participant_info":{"firstname":"ke379ccigitaraka","lastname":"ke379ccigitaraka","email":"ke379ccigitaraka@gmail.com"}},{"tid":"565","token":"ke774aicgategicdc","participant_info":{"firstname":"ke774aicgategicdc","lastname":"ke774aicgategicdc","email":"ke774aicgategicdc@gmail.com"}},{"tid":"567","token":"ke775aickarabacdc","participant_info":{"firstname":"ke775aickarabacdc","lastname":"ke775aickarabacdc","email":"ke775aickarabacdc@gmail.com"}},{"tid":"569","token":"ke777aicmakutanocdc","participant_info":{"firstname":"ke777aicmakutanocdc","lastname":"ke777aicmakutanocdc","email":"ke777aicmakutanocdc@gmail.com"}},{"tid":"571","token":"ke381dcnguutanicdc","participant_info":{"firstname":"ke381dcnguutanicdc","lastname":"ke381dcnguutanicdc","email":"ke381dcnguutanicdc@gmail.com"}},{"tid":"573","token":"ke384dcnzalaecdc","participant_info":{"firstname":"ke384dcnzalaecdc","lastname":"ke384dcnzalaecdc","email":"ke384dcnzalaecdc@gmail.com"}},{"tid":"575","token":"ke394rgcthokoacdc","participant_info":{"firstname":"ke394rgcthokoacdc","lastname":"ke394rgcthokoacdc","email":"ke394rgcthokoacdc@gmail.com"}},{"tid":"577","token":"ke764fgckkaluacdc","participant_info":{"firstname":"ke764fgckkaluacdc","lastname":"ke764fgckkaluacdc","email":"ke764fgckkaluacdc@gmail.com"}},{"tid":"579","token":"ke765fgckwaitacdc","participant_info":{"firstname":"ke765fgckwaitacdc","lastname":"ke765fgckwaitacdc","email":"ke765fgckwaitacdc@gmail.com"}},{"tid":"581","token":"ke766aiclundicdc","participant_info":{"firstname":"ke766aiclundicdc","lastname":"ke766aiclundicdc","email":"ke766aiclundicdc@gmail.com"}},{"tid":"583","token":"ke769fgckmisukinicdc","participant_info":{"firstname":"ke769fgckmisukinicdc","lastname":"ke769fgckmisukinicdc","email":"ke769fgckmisukinicdc@gmail.com"}},{"tid":"585","token":"ke776gfbcmbondonicdc","participant_info":{"firstname":"ke776gfbcmbondonicdc","lastname":"ke776gfbcmbondonicdc","email":"ke776gfbcmbondonicdc@gmail.com"}},{"tid":"587","token":"ke778aickathonzwenicdc","participant_info":{"firstname":"ke778aickathonzwenicdc","lastname":"ke778aickathonzwenicdc","email":"ke778aickathonzwenicdc@gmail.com"}},{"tid":"589","token":"ke781kiiogfbccdc","participant_info":{"firstname":"ke781kiiogfbccdc","lastname":"ke781kiiogfbccdc","email":"ke781kiiogfbccdc@gmail.com"}},{"tid":"591","token":"ke783aickithyokocdc","participant_info":{"firstname":"ke783aickithyokocdc","lastname":"ke783aickithyokocdc","email":"ke783aickithyokocdc@gmail.com"}},{"tid":"593","token":"ke784aicithumbicdc","participant_info":{"firstname":"ke784aicithumbicdc","lastname":"ke784aicithumbicdc","email":"ke784aicithumbicdc@gmail.com"}},{"tid":"595","token":"ke222chemichemicdc","participant_info":{"firstname":"ke222chemichemicdc","lastname":"ke222chemichemicdc","email":"ke222chemichemicdc@gmail.com"}},{"tid":"597","token":"ke320kagmlangokubwacdc","participant_info":{"firstname":"ke320kagmlangokubwacdc","lastname":"ke320kagmlangokubwacdc","email":"ke320kagmlangokubwacdc@gmail.com"}},{"tid":"599","token":"ke812ackmalangacdc","participant_info":{"firstname":"ke812ackmalangacdc","lastname":"ke812ackmalangacdc","email":"ke812ackmalangacdc@gmail.com"}},{"tid":"601","token":"ke813acksawagongocdc","participant_info":{"firstname":"ke813acksawagongocdc","lastname":"ke813acksawagongocdc","email":"ke813acksawagongocdc@gmail.com"}},{"tid":"603","token":"ke814acksimenyacdc","participant_info":{"firstname":"ke814acksimenyacdc","lastname":"ke814acksimenyacdc","email":"ke814acksimenyacdc@gmail.com"}},{"tid":"605","token":"ke816ackmunjiticdc","participant_info":{"firstname":"ke816ackmunjiticdc","lastname":"ke816ackmunjiticdc","email":"ke816ackmunjiticdc@gmail.com"}},{"tid":"607","token":"ke426cogibinzocdc","participant_info":{"firstname":"ke426cogibinzocdc","lastname":"ke426cogibinzocdc","email":"ke426cogibinzocdc@gmail.com"}},{"tid":"609","token":"ke560kolochcdc","participant_info":{"firstname":"ke560kolochcdc","lastname":"ke560kolochcdc","email":"ke560kolochcdc@gmail.com"}},{"tid":"611","token":"ke563seremcdc","participant_info":{"firstname":"ke563seremcdc","lastname":"ke563seremcdc","email":"ke563seremcdc@gmail.com"}},{"tid":"613","token":"ke819marabacdc","participant_info":{"firstname":"ke819marabacdc","lastname":"ke819marabacdc","email":"ke819marabacdc@gmail.com"}},{"tid":"615","token":"ke353ndumbericdc","participant_info":{"firstname":"ke353ndumbericdc","lastname":"ke353ndumbericdc","email":"ke353ndumbericdc@gmail.com"}},{"tid":"617","token":"ke370jipemoyowaithaka","participant_info":{"firstname":"ke370jipemoyowaithaka","lastname":"ke370jipemoyowaithaka","email":"ke370jipemoyowaithaka@gmail.com"}},{"tid":"619","token":"ke393ccijoyfamilyjja","participant_info":{"firstname":"ke393ccijoyfamilyjja","lastname":"ke393ccijoyfamilyjja","email":"ke393ccijoyfamilyjja@gmail.com"}},{"tid":"621","token":"ke395cciruiru","participant_info":{"firstname":"ke395cciruiru","lastname":"ke395cciruiru","email":"ke395cciruiru@gmail.com"}},{"tid":"623","token":"ke413kagkamaecdc","participant_info":{"firstname":"ke413kagkamaecdc","lastname":"ke413kagkamaecdc","email":"ke413kagkamaecdc@gmail.com"}},{"tid":"625","token":"ke451pefakiwanjacdc","participant_info":{"firstname":"ke451pefakiwanjacdc","lastname":"ke451pefakiwanjacdc","email":"ke451pefakiwanjacdc@gmail.com"}},{"tid":"627","token":"ke462kagkamirithu","participant_info":{"firstname":"ke462kagkamirithu","lastname":"ke462kagkamirithu","email":"ke462kagkamirithu@gmail.com"}},{"tid":"629","token":"ke611net","participant_info":{"firstname":"ke611net","lastname":"ke611net","email":"ke611net@gmail.com"}},{"tid":"631","token":"ke728aic","participant_info":{"firstname":"ke728aic","lastname":"ke728aic","email":"ke728aic@gmail.com"}},{"tid":"633","token":"ke907ngechacdc","participant_info":{"firstname":"ke907ngechacdc","lastname":"ke907ngechacdc","email":"ke907ngechacdc@gmail.com"}},{"tid":"635","token":"ke908pcearironicdc","participant_info":{"firstname":"ke908pcearironicdc","lastname":"ke908pcearironicdc","email":"ke908pcearironicdc@gmail.com"}},{"tid":"637","token":"ke913pceakangoyacdc","participant_info":{"firstname":"ke913pceakangoyacdc","lastname":"ke913pceakangoyacdc","email":"ke913pceakangoyacdc@gmail.com"}},{"tid":"639","token":"ke917pceaevergreencdc","participant_info":{"firstname":"ke917pceaevergreencdc","lastname":"ke917pceaevergreencdc","email":"ke917pceaevergreencdc@gmail.com"}},{"tid":"641","token":"ke921pceakamiticdc","participant_info":{"firstname":"ke921pceakamiticdc","lastname":"ke921pceakamiticdc","email":"ke921pceakamiticdc@gmail.com"}},{"tid":"643","token":"ke0286benezercdc","participant_info":{"firstname":"ke0286benezercdc","lastname":"ke0286benezercdc","email":"ke0286benezercdc@gmail.com"}},{"tid":"645","token":"ke0287kagkaembeni","participant_info":{"firstname":"ke0287kagkaembeni","lastname":"ke0287kagkaembeni","email":"ke0287kagkaembeni@gmail.com"}},{"tid":"647","token":"ke0288tuzo","participant_info":{"firstname":"ke0288tuzo","lastname":"ke0288tuzo","email":"ke0288tuzo@gmail.com"}},{"tid":"649","token":"ke0289ushindibaptistcdc","participant_info":{"firstname":"ke0289ushindibaptistcdc","lastname":"ke0289ushindibaptistcdc","email":"ke0289ushindibaptistcdc@gmail.com"}},{"tid":"651","token":"ke342jfcccdc","participant_info":{"firstname":"ke342jfcccdc","lastname":"ke342jfcccdc","email":"ke342jfcccdc@gmail.com"}},{"tid":"653","token":"ke347gospelrevivalcdc","participant_info":{"firstname":"ke347gospelrevivalcdc","lastname":"ke347gospelrevivalcdc","email":"ke347gospelrevivalcdc@gmail.com"}},{"tid":"655","token":"ke530mtondiapefacdc","participant_info":{"firstname":"ke530mtondiapefacdc","lastname":"ke530mtondiapefacdc","email":"ke530mtondiapefacdc@gmail.com"}},{"tid":"657","token":"ke622aickilifi","participant_info":{"firstname":"ke622aickilifi","lastname":"ke622aickilifi","email":"ke622aickilifi@gmail.com"}},{"tid":"659","token":"ke400kimacogcdc","participant_info":{"firstname":"ke400kimacogcdc","lastname":"ke400kimacogcdc","email":"ke400kimacogcdc@gmail.com"}},{"tid":"661","token":"ke403cogebusiralocdc","participant_info":{"firstname":"ke403cogebusiralocdc","lastname":"ke403cogebusiralocdc","email":"ke403cogebusiralocdc@gmail.com"}},{"tid":"663","token":"ke404essunzacdc","participant_info":{"firstname":"ke404essunzacdc","lastname":"ke404essunzacdc","email":"ke404essunzacdc@gmail.com"}},{"tid":"665","token":"ke405esirabecogcdc","participant_info":{"firstname":"ke405esirabecogcdc","lastname":"ke405esirabecogcdc","email":"ke405esirabecogcdc@gmail.com"}},{"tid":"667","token":"ke411cogmulwandacdc","participant_info":{"firstname":"ke411cogmulwandacdc","lastname":"ke411cogmulwandacdc","email":"ke411cogmulwandacdc@gmail.com"}},{"tid":"669","token":"ke412burendwacdc","participant_info":{"firstname":"ke412burendwacdc","lastname":"ke412burendwacdc","email":"ke412burendwacdc@gmail.com"}},{"tid":"671","token":"ke414cofgmatiolicdc","participant_info":{"firstname":"ke414cofgmatiolicdc","lastname":"ke414cofgmatiolicdc","email":"ke414cofgmatiolicdc@gmail.com"}},{"tid":"673","token":"ke420imusalicdc","participant_info":{"firstname":"ke420imusalicdc","lastname":"ke420imusalicdc","email":"ke420imusalicdc@gmail.com"}},{"tid":"675","token":"ke817ackimbalecdc","participant_info":{"firstname":"ke817ackimbalecdc","lastname":"ke817ackimbalecdc","email":"ke817ackimbalecdc@gmail.com"}},{"tid":"677","token":"ke818ackstemmutsacdc","participant_info":{"firstname":"ke818ackstemmutsacdc","lastname":"ke818ackstemmutsacdc","email":"ke818ackstemmutsacdc@gmail.com"}},{"tid":"679","token":"ke825emulunyacdc","participant_info":{"firstname":"ke825emulunyacdc","lastname":"ke825emulunyacdc","email":"ke825emulunyacdc@gmail.com"}},{"tid":"681","token":"ke828ackstpaulswandechecdc","participant_info":{"firstname":"ke828ackstpaulswandechecdc","lastname":"ke828ackstpaulswandechecdc","email":"ke828ackstpaulswandechecdc@gmail.com"}},{"tid":"683","token":"ke328pefamtaacdc","participant_info":{"firstname":"ke328pefamtaacdc","lastname":"ke328pefamtaacdc","email":"ke328pefamtaacdc@gmail.com"}},{"tid":"685","token":"ke329eapcmabeshenicdc","participant_info":{"firstname":"ke329eapcmabeshenicdc","lastname":"ke329eapcmabeshenicdc","email":"ke329eapcmabeshenicdc@gmail.com"}},{"tid":"687","token":"ke331mazolacdc","participant_info":{"firstname":"ke331mazolacdc","lastname":"ke331mazolacdc","email":"ke331mazolacdc@gmail.com"}},{"tid":"689","token":"ke332eapccdckinango","participant_info":{"firstname":"ke332eapccdckinango","lastname":"ke332eapccdckinango","email":"ke332eapccdckinango@gmail.com"}},{"tid":"691","token":"ke346pefabofucdc","participant_info":{"firstname":"ke346pefabofucdc","lastname":"ke346pefabofucdc","email":"ke346pefabofucdc@gmail.com"}},{"tid":"693","token":"ke388bonjepefacdc","participant_info":{"firstname":"ke388bonjepefacdc","lastname":"ke388bonjepefacdc","email":"ke388bonjepefacdc@gmail.com"}},{"tid":"695","token":"ke389pefamaweucdc","participant_info":{"firstname":"ke389pefamaweucdc","lastname":"ke389pefamaweucdc","email":"ke389pefamaweucdc@gmail.com"}},{"tid":"697","token":"ke556miatsanicdc","participant_info":{"firstname":"ke556miatsanicdc","lastname":"ke556miatsanicdc","email":"ke556miatsanicdc@gmail.com"}},{"tid":"699","token":"ke596baptistmigunenicdc","participant_info":{"firstname":"ke596baptistmigunenicdc","lastname":"ke596baptistmigunenicdc","email":"ke596baptistmigunenicdc@gmail.com"}},{"tid":"701","token":"ke597nzovunibaptistcdc","participant_info":{"firstname":"ke597nzovunibaptistcdc","lastname":"ke597nzovunibaptistcdc","email":"ke597nzovunibaptistcdc@gmail.com"}},{"tid":"703","token":"ke645ackkwalecdc","participant_info":{"firstname":"ke645ackkwalecdc","lastname":"ke645ackkwalecdc","email":"ke645ackkwalecdc@gmail.com"}},{"tid":"705","token":"ke710mckkinangocdc","participant_info":{"firstname":"ke710mckkinangocdc","lastname":"ke710mckkinangocdc","email":"ke710mckkinangocdc@gmail.com"}},{"tid":"707","token":"ke711mckbundinicdc","participant_info":{"firstname":"ke711mckbundinicdc","lastname":"ke711mckbundinicdc","email":"ke711mckbundinicdc@gmail.com"}},{"tid":"709","token":"ke716aicmajengocdc","participant_info":{"firstname":"ke716aicmajengocdc","lastname":"ke716aicmajengocdc","email":"ke716aicmajengocdc@gmail.com"}},{"tid":"711","token":"ke789chiguturgccdc","participant_info":{"firstname":"ke789chiguturgccdc","lastname":"ke789chiguturgccdc","email":"ke789chiguturgccdc@gmail.com"}},{"tid":"713","token":"ke460gncayuumbucdc","participant_info":{"firstname":"ke460gncayuumbucdc","lastname":"ke460gncayuumbucdc","email":"ke460gncayuumbucdc@gmail.com"}},{"tid":"715","token":"ke600ackkwandonga","participant_info":{"firstname":"ke600ackkwandonga","lastname":"ke600ackkwandonga","email":"ke600ackkwandonga@gmail.com"}},{"tid":"717","token":"ke603kyanikacdc","participant_info":{"firstname":"ke603kyanikacdc","lastname":"ke603kyanikacdc","email":"ke603kyanikacdc@gmail.com"}},{"tid":"719","token":"ke643kakumicdc","participant_info":{"firstname":"ke643kakumicdc","lastname":"ke643kakumicdc","email":"ke643kakumicdc@gmail.com"}},{"tid":"721","token":"ke745kiiniaic","participant_info":{"firstname":"ke745kiiniaic","lastname":"ke745kiiniaic","email":"ke745kiiniaic@gmail.com"}},{"tid":"723","token":"ke746aicikangacdc","participant_info":{"firstname":"ke746aicikangacdc","lastname":"ke746aicikangacdc","email":"ke746aicikangacdc@gmail.com"}},{"tid":"725","token":"ke747gncaenzoucdc","participant_info":{"firstname":"ke747gncaenzoucdc","lastname":"ke747gncaenzoucdc","email":"ke747gncaenzoucdc@gmail.com"}},{"tid":"727","token":"ke748rgcmutomocdc","participant_info":{"firstname":"ke748rgcmutomocdc","lastname":"ke748rgcmutomocdc","email":"ke748rgcmutomocdc@gmail.com"}},{"tid":"729","token":"ke749eapckyoanicdc","participant_info":{"firstname":"ke749eapckyoanicdc","lastname":"ke749eapckyoanicdc","email":"ke749eapckyoanicdc@gmail.com"}},{"tid":"731","token":"ke751gncakyatunecdc","participant_info":{"firstname":"ke751gncakyatunecdc","lastname":"ke751gncakyatunecdc","email":"ke751gncakyatunecdc@gmail.com"}},{"tid":"733","token":"ke752rgcchulunicdc","participant_info":{"firstname":"ke752rgcchulunicdc","lastname":"ke752rgcchulunicdc","email":"ke752rgcchulunicdc@gmail.com"}},{"tid":"735","token":"ke757aicnthangathinicdc","participant_info":{"firstname":"ke757aicnthangathinicdc","lastname":"ke757aicnthangathinicdc","email":"ke757aicnthangathinicdc@gmail.com"}},{"tid":"737","token":"ke280rgcnanyukicdc","participant_info":{"firstname":"ke280rgcnanyukicdc","lastname":"ke280rgcnanyukicdc","email":"ke280rgcnanyukicdc@gmail.com"}},{"tid":"739","token":"ke281fgckchumvicdc","participant_info":{"firstname":"ke281fgckchumvicdc","lastname":"ke281fgckchumvicdc","email":"ke281fgckchumvicdc@gmail.com"}},{"tid":"741","token":"ke282pceakimanjocdc","participant_info":{"firstname":"ke282pceakimanjocdc","lastname":"ke282pceakimanjocdc","email":"ke282pceakimanjocdc@gmail.com"}},{"tid":"743","token":"ke283pceasiraimm2","participant_info":{"firstname":"ke283pceasiraimm2","lastname":"ke283pceasiraimm2","email":"ke283pceasiraimm2@gmail.com"}},{"tid":"745","token":"ke284dcolmorancdc","participant_info":{"firstname":"ke284dcolmorancdc","lastname":"ke284dcolmorancdc","email":"ke284dcolmorancdc@gmail.com"}},{"tid":"747","token":"ke285fgckmainacdc","participant_info":{"firstname":"ke285fgckmainacdc","lastname":"ke285fgckmainacdc","email":"ke285fgckmainacdc@gmail.com"}},{"tid":"749","token":"ke313episcopalcdc","participant_info":{"firstname":"ke313episcopalcdc","lastname":"ke313episcopalcdc","email":"ke313episcopalcdc@gmail.com"}},{"tid":"751","token":"ke356dorcascdc","participant_info":{"firstname":"ke356dorcascdc","lastname":"ke356dorcascdc","email":"ke356dorcascdc@gmail.com"}},{"tid":"753","token":"ke364pagbuoye","participant_info":{"firstname":"ke364pagbuoye","lastname":"ke364pagbuoye","email":"ke364pagbuoye@gmail.com"}},{"tid":"755","token":"ke365geecdc","participant_info":{"firstname":"ke365geecdc","lastname":"ke365geecdc","email":"ke365geecdc@gmail.com"}},{"tid":"757","token":"ke376kagsiany","participant_info":{"firstname":"ke376kagsiany","lastname":"ke376kagsiany","email":"ke376kagsiany@gmail.com"}},{"tid":"759","token":"ke377ecastbarnabascdc","participant_info":{"firstname":"ke377ecastbarnabascdc","lastname":"ke377ecastbarnabascdc","email":"ke377ecastbarnabascdc@gmail.com"}},{"tid":"761","token":"ke387elckcdc","participant_info":{"firstname":"ke387elckcdc","lastname":"ke387elckcdc","email":"ke387elckcdc@gmail.com"}},{"tid":"763","token":"ke434keytolifecdc","participant_info":{"firstname":"ke434keytolifecdc","lastname":"ke434keytolifecdc","email":"ke434keytolifecdc@gmail.com"}},{"tid":"765","token":"ke805mahayacdc","participant_info":{"firstname":"ke805mahayacdc","lastname":"ke805mahayacdc","email":"ke805mahayacdc@gmail.com"}},{"tid":"767","token":"ke806manyattacdc","participant_info":{"firstname":"ke806manyattacdc","lastname":"ke806manyattacdc","email":"ke806manyattacdc@gmail.com"}},{"tid":"769","token":"ke807ackranalocdc","participant_info":{"firstname":"ke807ackranalocdc","lastname":"ke807ackranalocdc","email":"ke807ackranalocdc@gmail.com"}},{"tid":"771","token":"ke808lweyacdc","participant_info":{"firstname":"ke808lweyacdc","lastname":"ke808lweyacdc","email":"ke808lweyacdc@gmail.com"}},{"tid":"773","token":"ke809nyagokocdc","participant_info":{"firstname":"ke809nyagokocdc","lastname":"ke809nyagokocdc","email":"ke809nyagokocdc@gmail.com"}},{"tid":"775","token":"ke223fpfkemalicdc","participant_info":{"firstname":"ke223fpfkemalicdc","lastname":"ke223fpfkemalicdc","email":"ke223fpfkemalicdc@gmail.com"}},{"tid":"777","token":"ke233aickalambacdc","participant_info":{"firstname":"ke233aickalambacdc","lastname":"ke233aickalambacdc","email":"ke233aickalambacdc@gmail.com"}},{"tid":"779","token":"ke234gfbcthavucdc","participant_info":{"firstname":"ke234gfbcthavucdc","lastname":"ke234gfbcthavucdc","email":"ke234gfbcthavucdc@gmail.com"}},{"tid":"781","token":"ke235gncakikuminicdc","participant_info":{"firstname":"ke235gncakikuminicdc","lastname":"ke235gncakikuminicdc","email":"ke235gncakikuminicdc@gmail.com"}},{"tid":"783","token":"ke236gncamakinducdc","participant_info":{"firstname":"ke236gncamakinducdc","lastname":"ke236gncamakinducdc","email":"ke236gncamakinducdc@gmail.com"}},{"tid":"785","token":"ke237aicmakutanocdc","participant_info":{"firstname":"ke237aicmakutanocdc","lastname":"ke237aicmakutanocdc","email":"ke237aicmakutanocdc@gmail.com"}},{"tid":"787","token":"ke238aicmatingacdc","participant_info":{"firstname":"ke238aicmatingacdc","lastname":"ke238aicmatingacdc","email":"ke238aicmatingacdc@gmail.com"}},{"tid":"789","token":"ke239baptistkathyakacdc","participant_info":{"firstname":"ke239baptistkathyakacdc","lastname":"ke239baptistkathyakacdc","email":"ke239baptistkathyakacdc@gmail.com"}},{"tid":"791","token":"ke240rgcmasongalenicdc","participant_info":{"firstname":"ke240rgcmasongalenicdc","lastname":"ke240rgcmasongalenicdc","email":"ke240rgcmasongalenicdc@gmail.com"}},{"tid":"793","token":"ke241aickalawacdc","participant_info":{"firstname":"ke241aickalawacdc","lastname":"ke241aickalawacdc","email":"ke241aickalawacdc@gmail.com"}},{"tid":"795","token":"ke244gfbcmbumbunicdc","participant_info":{"firstname":"ke244gfbcmbumbunicdc","lastname":"ke244gfbcmbumbunicdc","email":"ke244gfbcmbumbunicdc@gmail.com"}},{"tid":"797","token":"ke245rgckavetecdc","participant_info":{"firstname":"ke245rgckavetecdc","lastname":"ke245rgckavetecdc","email":"ke245rgckavetecdc@gmail.com"}},{"tid":"799","token":"ke246pagnthongonicdc","participant_info":{"firstname":"ke246pagnthongonicdc","lastname":"ke246pagnthongonicdc","email":"ke246pagnthongonicdc@gmail.com"}},{"tid":"801","token":"ke343wesapefacdc","participant_info":{"firstname":"ke343wesapefacdc","lastname":"ke343wesapefacdc","email":"ke343wesapefacdc@gmail.com"}},{"tid":"803","token":"ke344cdcmtanganirgc","participant_info":{"firstname":"ke344cdcmtanganirgc","lastname":"ke344cdcmtanganirgc","email":"ke344cdcmtanganirgc@gmail.com"}},{"tid":"805","token":"ke345pefadabaso","participant_info":{"firstname":"ke345pefadabaso","lastname":"ke345pefadabaso","email":"ke345pefadabaso@gmail.com"}},{"tid":"807","token":"ke392mkonganiifccdc","participant_info":{"firstname":"ke392mkonganiifccdc","lastname":"ke392mkonganiifccdc","email":"ke392mkonganiifccdc@gmail.com"}},{"tid":"809","token":"ke0512pefagodkwercydc","participant_info":{"firstname":"ke0512pefagodkwercydc","lastname":"ke0512pefagodkwercydc","email":"ke0512pefagodkwercydc@gmail.com"}},{"tid":"811","token":"ke0513pefakurutiyangecydc","participant_info":{"firstname":"ke0513pefakurutiyangecydc","lastname":"ke0513pefakurutiyangecydc","email":"ke0513pefakurutiyangecydc@gmail.com"}},{"tid":"813","token":"ke0514pefagwitembecydc","participant_info":{"firstname":"ke0514pefagwitembecydc","lastname":"ke0514pefagwitembecydc","email":"ke0514pefagwitembecydc@gmail.com"}},{"tid":"815","token":"ke737aickiseriancdc","participant_info":{"firstname":"ke737.aickiseriancdc","lastname":"ke737.aickiseriancdc","email":"ke737.aickiseriancdc@gmail.com"}},{"tid":"817","token":"ke307enoosaen","participant_info":{"firstname":"ke307.enoosaen","lastname":"ke307.enoosaen","email":"ke307.enoosaen@gmail.com"}},{"tid":"819","token":"ke363enenkeshui","participant_info":{"firstname":"ke363.enenkeshui","lastname":"ke363.enenkeshui","email":"ke363.enenkeshui@gmail.com"}},{"tid":"821","token":"ke337eapccdc","participant_info":{"firstname":"ke337e.a.p.c.cdc","lastname":"ke337e.a.p.c.cdc","email":"ke337e.a.p.c.cdc@gmail.com"}},{"tid":"823","token":"ke787aicmashehenicdc","participant_info":{"firstname":"ke.787.aic.masheheni.cdc","lastname":"ke.787.aic.masheheni.cdc","email":"ke.787.aic.masheheni.cdc@gmail.com"}},{"tid":"825","token":"ke641ackstsimeonmazeras","participant_info":{"firstname":"ke641ackst.simeonmazeras","lastname":"ke641ackst.simeonmazeras","email":"ke641ackst.simeonmazeras@gmail.com"}},{"tid":"827","token":"ke355matharecommoutreachcdc","participant_info":{"firstname":"ke355matharecomm.outreachcdc","lastname":"ke355matharecomm.outreachcdc","email":"ke355matharecomm.outreachcdc@gmail.com"}},{"tid":"831","token":"fNLG9w9QHnbRrw7","participant_info":{"firstname":"Nick","lastname":"Karisa","email":"mwambirekarisa2017@gmail.com"}},{"tid":"833","token":"YudM2XM355RnztK","participant_info":{"firstname":"Odhiambo","lastname":"Velma","email":"ckeptsu@gmail.com"}}]